mctorch/__init__.py
mctorch/nn/__init__.py
mctorch/nn/parameter.py
mctorch/nn/manifolds/__init__.py
mctorch/nn/manifolds/euclidean.py
mctorch/nn/manifolds/hyperbolic.py
mctorch/nn/manifolds/manifold.py
mctorch/nn/manifolds/manifold_factory.py
mctorch/nn/manifolds/positive_definite.py
mctorch/nn/manifolds/stiefel.py
mctorch/nn/modules/__init__.py
mctorch/nn/modules/conv.py
mctorch/nn/modules/linear.py
mctorch/nn/modules/utils.py
mctorch/nn/utils/__init__.py
mctorch/nn/utils/manifold_multi.py
mctorch/optim/__init__.py
mctorch/optim/conjugate_gradient.py
mctorch/optim/radagrad.py
mctorch/optim/rsgd.py
mctorch_lib-0.1.0.dist-info/LICENSE
mctorch_lib-0.1.0.dist-info/METADATA
mctorch_lib-0.1.0.dist-info/WHEEL
mctorch_lib-0.1.0.dist-info/top_level.txt
mctorch_lib-0.1.0.dist-info/RECORD
