Metadata-Version: 2.1
Name: mctorch-lib
Version: 0.1.0
Summary: McTorch, a manifold optimization library for deep learning
Home-page: https://github.com/mctorch/mctorch_lib
Author: McTorch Team
Author-email: mayankmeghwanshi@gmail.com
License: UNKNOWN
Platform: UNKNOWN
Classifier: Programming Language :: Python :: 3
Classifier: License :: OSI Approved :: MIT License
Classifier: Operating System :: OS Independent
Requires-Python: >=3.6
Requires-Dist: torch
Requires-Dist: numpy
